actor_rtc-0.1.0.dist-info/METADATA
actor_rtc-0.1.0.dist-info/WHEEL
actor_rtc/__init__.py
actor_rtc/actor_rtc.cpython-312-darwin.so
actor_rtc-0.1.0.dist-info/RECORD
