Metadata-Version: 2.4
Name: actor_rtc
Version: 0.1.0
Classifier: Programming Language :: Rust
Classifier: Programming Language :: Python :: Implementation :: CPython
Classifier: Programming Language :: Python :: Implementation :: PyPy
Summary: Actor RTC bindings for Python
Keywords: actor,web-rtc,signaling
Requires-Python: >=3.8
Project-URL: Source Code, https://gitlab.huanqiu-ltd.com/platform/actor-rtc
